Metadata-Version: 2.1
Name: bpnotify
Version: 0.50
Summary: Notification routing for Django
Author-email: "BeProud Inc." <project@beproud.jp>
Project-URL: Homepage, https://github.com/beproud/bpnotify/
Keywords: django
Classifier: Development Status :: 3 - Alpha
Classifier: License :: OSI Approved :: BSD License
Classifier: Programming Language :: Python
Classifier: Programming Language :: Python :: 3
Classifier: Programming Language :: Python :: 3.9
Classifier: Programming Language :: Python :: 3.10
Classifier: Programming Language :: Python :: 3.11
Classifier: Programming Language :: Python :: 3.12
Classifier: Framework :: Django
Classifier: Framework :: Django :: 4.2
Classifier: Intended Audience :: Developers
Classifier: Environment :: Plugins
Classifier: Topic :: Software Development :: Libraries :: Python Modules
Requires-Python: >=3.9
Requires-Dist: Django>=4.2
Requires-Dist: six
Requires-Dist: Celery
